gooddata_fdw/__init__.py
gooddata_fdw/_version.py
gooddata_fdw/column_utils.py
gooddata_fdw/column_validation.py
gooddata_fdw/environment.py
gooddata_fdw/executor.py
gooddata_fdw/fdw.py
gooddata_fdw/filter.py
gooddata_fdw/import_workspace.py
gooddata_fdw/naming.py
gooddata_fdw/options.py
gooddata_fdw/pg_logging.py
gooddata_fdw/result_reader.py
gooddata_fdw-1.58.0.dist-info/METADATA
gooddata_fdw-1.58.0.dist-info/WHEEL
gooddata_fdw-1.58.0.dist-info/licenses/LICENSE.txt
gooddata_fdw-1.58.0.dist-info/RECORD
